{"widgets":[{"height":6,"properties":{"metrics":[["AWS/EC2","CPUUtilization","AutoScalingGroupName","bootcamp-project-dev-asg"]],"period":60,"region":"eu-central-1","title":"CPU Utilization"},"type":"metric","width":12,"x":0,"y":0},{"height":6,"properties":{"metrics":[["AWS/ApplicationELB","RequestCount","LoadBalancer","app/bootcamp-project-dev-alb/2dfb78a3f0c8aba6"]],"period":60,"region":"eu-central-1","title":"ALB Request Count"},"type":"metric","width":12,"x":12,"y":0},{"height":6,"properties":{"metrics":[["AWS/ApplicationELB","TargetResponseTime","LoadBalancer","app/bootcamp-project-dev-alb/2dfb78a3f0c8aba6"]],"period":60,"region":"eu-central-1","title":"Target Response Time"},"type":"metric","width":12,"x":0,"y":6},{"height":6,"properties":{"metrics":[["AWS/ApplicationELB","UnHealthyHostCount","LoadBalancer","app/bootcamp-project-dev-alb/2dfb78a3f0c8aba6","TargetGroup","targetgroup/bootcamp-project-dev-tg/463f1b97e26c16ae"]],"period":60,"region":"eu-central-1","title":"Unhealthy Host Count"},"type":"metric","width":12,"x":12,"y":6}]}
